[{"id":1,"full_name":"Aggi Benjamin","email":"abenjamin0@ning.com","gender":"Female","location":"Germany","username":"abenjamin0","image":"http://dummyimage.com/224x314.png/ff4444/ffffff","native":false},
{"id":2,"full_name":"Zoe Clemes","email":"zclemes1@wufoo.com","gender":"Genderfluid","location":"Germany","username":"zclemes1","image":"http://dummyimage.com/168x102.png/5fa2dd/ffffff","native":true},
{"id":3,"full_name":"Valle Blamey","email":"vblamey2@slate.com","gender":"Non-binary","location":"Germany","username":"vblamey2","image":"http://dummyimage.com/205x180.png/cc0000/ffffff","native":false},
{"id":4,"full_name":"Meaghan Balme","email":"mbalme3@clickbank.net","gender":"Male","location":"Germany","username":"mbalme3","image":"http://dummyimage.com/137x230.png/dddddd/000000","native":false},
{"id":5,"full_name":"Tawnya Jeste","email":"tjeste4@ucla.edu","gender":"Polygender","location":"Germany","username":"tjeste4","image":"http://dummyimage.com/166x202.png/5fa2dd/ffffff","native":false},
{"id":6,"full_name":"Bill Marquot","email":"bmarquot5@icq.com","gender":"Non-binary","location":"Germany","username":"bmarquot5","image":"http://dummyimage.com/217x163.png/dddddd/000000","native":true},
{"id":7,"full_name":"Izzy Iannetti","email":"iiannetti6@mozilla.org","gender":"Bigender","location":"Germany","username":"iiannetti6","image":"http://dummyimage.com/188x192.png/cc0000/ffffff","native":true},
{"id":8,"full_name":"Cornelius Vollam","email":"cvollam7@mozilla.com","gender":"Bigender","location":"Germany","username":"cvollam7","image":"http://dummyimage.com/207x146.png/dddddd/000000","native":false},
{"id":9,"full_name":"Gilligan Bonevant","email":"gbonevant8@uol.com.br","gender":"Agender","location":"Germany","username":"gbonevant8","image":"http://dummyimage.com/148x336.png/dddddd/000000","native":false},
{"id":10,"full_name":"Gale Zanioletti","email":"gzanioletti9@guardian.co.uk","gender":"Male","location":"Germany","username":"gzanioletti9","image":"http://dummyimage.com/209x281.png/dddddd/000000","native":true},
{"id":11,"full_name":"Cissiee Waddington","email":"cwaddingtona@elpais.com","gender":"Bigender","location":"Germany","username":"cwaddingtona","image":"http://dummyimage.com/120x181.png/cc0000/ffffff","native":false},
{"id":12,"full_name":"Alexandro Kunzel","email":"akunzelb@ox.ac.uk","gender":"Agender","location":"Germany","username":"akunzelb","image":"http://dummyimage.com/173x293.png/dddddd/000000","native":true},
{"id":13,"full_name":"Neale Geistbeck","email":"ngeistbeckc@amazon.com","gender":"Polygender","location":"Germany","username":"ngeistbeckc","image":"http://dummyimage.com/170x241.png/ff4444/ffffff","native":false},
{"id":14,"full_name":"Cornie MacAulay","email":"cmacaulayd@addthis.com","gender":"Male","location":"Germany","username":"cmacaulayd","image":"http://dummyimage.com/101x284.png/5fa2dd/ffffff","native":true},
{"id":15,"full_name":"Yardley Spoors","email":"yspoorse@jiathis.com","gender":"Agender","location":"Germany","username":"yspoorse","image":"http://dummyimage.com/178x296.png/cc0000/ffffff","native":false},
{"id":16,"full_name":"Cedric Hoopper","email":"choopperf@earthlink.net","gender":"Agender","location":"Germany","username":"choopperf","image":"http://dummyimage.com/229x271.png/ff4444/ffffff","native":true},
{"id":17,"full_name":"Consuela Jolliman","email":"cjollimang@yolasite.com","gender":"Genderqueer","location":"Germany","username":"cjollimang","image":"http://dummyimage.com/118x289.png/5fa2dd/ffffff","native":false},
{"id":18,"full_name":"Jerry Anniwell","email":"janniwellh@dagondesign.com","gender":"Male","location":"Germany","username":"janniwellh","image":"http://dummyimage.com/129x278.png/ff4444/ffffff","native":true},
{"id":19,"full_name":"Shermie Elderton","email":"seldertoni@digg.com","gender":"Bigender","location":"Germany","username":"seldertoni","image":"http://dummyimage.com/138x133.png/dddddd/000000","native":false},
{"id":20,"full_name":"Rickie Kearford","email":"rkearfordj@is.gd","gender":"Male","location":"Germany","username":"rkearfordj","image":"http://dummyimage.com/156x215.png/ff4444/ffffff","native":true},
{"id":21,"full_name":"Keri Van Baaren","email":"kvank@arizona.edu","gender":"Agender","location":"Germany","username":"kvank","image":"http://dummyimage.com/162x314.png/cc0000/ffffff","native":false},
{"id":22,"full_name":"Shell Halse","email":"shalsel@bigcartel.com","gender":"Male","location":"Germany","username":"shalsel","image":"http://dummyimage.com/115x112.png/cc0000/ffffff","native":true},
{"id":23,"full_name":"Leyla Hemshall","email":"lhemshallm@tmall.com","gender":"Genderqueer","location":"Germany","username":"lhemshallm","image":"http://dummyimage.com/156x242.png/cc0000/ffffff","native":false},
{"id":24,"full_name":"Josy Haycraft","email":"jhaycraftn@psu.edu","gender":"Bigender","location":"Germany","username":"jhaycraftn","image":"http://dummyimage.com/236x198.png/5fa2dd/ffffff","native":true},
{"id":25,"full_name":"Meghann Bonn","email":"mbonno@hao123.com","gender":"Non-binary","location":"Germany","username":"mbonno","image":"http://dummyimage.com/241x342.png/5fa2dd/ffffff","native":true},
{"id":26,"full_name":"Franky Jouannot","email":"fjouannotp@tinypic.com","gender":"Bigender","location":"Germany","username":"fjouannotp","image":"http://dummyimage.com/238x242.png/cc0000/ffffff","native":false},
{"id":27,"full_name":"Torr Joost","email":"tjoostq@weibo.com","gender":"Genderqueer","location":"Germany","username":"tjoostq","image":"http://dummyimage.com/191x238.png/dddddd/000000","native":false},
{"id":28,"full_name":"Corena Whawell","email":"cwhawellr@squidoo.com","gender":"Genderqueer","location":"Germany","username":"cwhawellr","image":"http://dummyimage.com/122x174.png/dddddd/000000","native":true},
{"id":29,"full_name":"Alfreda Sempill","email":"asempills@tinyurl.com","gender":"Genderfluid","location":"Germany","username":"asempills","image":"http://dummyimage.com/191x137.png/5fa2dd/ffffff","native":true},
{"id":30,"full_name":"Verne Siccombe","email":"vsiccombet@pen.io","gender":"Agender","location":"Germany","username":"vsiccombet","image":"http://dummyimage.com/137x279.png/dddddd/000000","native":true},
{"id":31,"full_name":"Audrye Tackes","email":"atackesu@last.fm","gender":"Bigender","location":"Germany","username":"atackesu","image":"http://dummyimage.com/231x216.png/cc0000/ffffff","native":false},
{"id":32,"full_name":"Millisent Mellanby","email":"mmellanbyv@360.cn","gender":"Genderfluid","location":"Germany","username":"mmellanbyv","image":"http://dummyimage.com/226x220.png/cc0000/ffffff","native":true},
{"id":33,"full_name":"Tanhya Dunne","email":"tdunnew@etsy.com","gender":"Male","location":"Germany","username":"tdunnew","image":"http://dummyimage.com/101x257.png/cc0000/ffffff","native":true},
{"id":34,"full_name":"Haily Benardet","email":"hbenardetx@slashdot.org","gender":"Non-binary","location":"Germany","username":"hbenardetx","image":"http://dummyimage.com/183x136.png/5fa2dd/ffffff","native":false},
{"id":35,"full_name":"Katrine Vye","email":"kvyey@github.com","gender":"Agender","location":"Germany","username":"kvyey","image":"http://dummyimage.com/224x152.png/cc0000/ffffff","native":true},
{"id":36,"full_name":"Jessalyn Hassan","email":"jhassanz@cornell.edu","gender":"Agender","location":"Germany","username":"jhassanz","image":"http://dummyimage.com/149x341.png/cc0000/ffffff","native":false},
{"id":37,"full_name":"Lucias Thornber","email":"lthornber10@tuttocitta.it","gender":"Polygender","location":"Germany","username":"lthornber10","image":"http://dummyimage.com/109x265.png/ff4444/ffffff","native":true},
{"id":38,"full_name":"Esther Feeny","email":"efeeny11@sogou.com","gender":"Non-binary","location":"Germany","username":"efeeny11","image":"http://dummyimage.com/167x182.png/ff4444/ffffff","native":true},
{"id":39,"full_name":"Anderson Gerge","email":"agerge12@squidoo.com","gender":"Non-binary","location":"Germany","username":"agerge12","image":"http://dummyimage.com/109x302.png/cc0000/ffffff","native":true},
{"id":40,"full_name":"Herby Balducci","email":"hbalducci13@chicagotribune.com","gender":"Genderqueer","location":"Germany","username":"hbalducci13","image":"http://dummyimage.com/212x260.png/ff4444/ffffff","native":true},
{"id":41,"full_name":"Lora Godball","email":"lgodball14@odnoklassniki.ru","gender":"Agender","location":"Germany","username":"lgodball14","image":"http://dummyimage.com/232x103.png/ff4444/ffffff","native":true},
{"id":42,"full_name":"Wyndham Castille","email":"wcastille15@google.com","gender":"Non-binary","location":"Germany","username":"wcastille15","image":"http://dummyimage.com/245x166.png/dddddd/000000","native":false},
{"id":43,"full_name":"Norri Ommundsen","email":"nommundsen16@tinypic.com","gender":"Genderqueer","location":"Germany","username":"nommundsen16","image":"http://dummyimage.com/193x214.png/ff4444/ffffff","native":true},
{"id":44,"full_name":"Toni Pechet","email":"tpechet17@tamu.edu","gender":"Male","location":"Germany","username":"tpechet17","image":"http://dummyimage.com/139x179.png/dddddd/000000","native":false},
{"id":45,"full_name":"Stanislaw Jobbins","email":"sjobbins18@army.mil","gender":"Male","location":"Germany","username":"sjobbins18","image":"http://dummyimage.com/231x181.png/ff4444/ffffff","native":false},
{"id":46,"full_name":"Zorah Bugler","email":"zbugler19@uol.com.br","gender":"Non-binary","location":"Germany","username":"zbugler19","image":"http://dummyimage.com/181x327.png/ff4444/ffffff","native":false},
{"id":47,"full_name":"Wheeler Figurski","email":"wfigurski1a@sitemeter.com","gender":"Female","location":"Germany","username":"wfigurski1a","image":"http://dummyimage.com/205x160.png/cc0000/ffffff","native":false},
{"id":48,"full_name":"Corabelle Pugsley","email":"cpugsley1b@qq.com","gender":"Non-binary","location":"Germany","username":"cpugsley1b","image":"http://dummyimage.com/140x184.png/dddddd/000000","native":false},
{"id":49,"full_name":"Shirlee Michelet","email":"smichelet1c@salon.com","gender":"Polygender","location":"Germany","username":"smichelet1c","image":"http://dummyimage.com/237x309.png/dddddd/000000","native":true},
{"id":50,"full_name":"Fred Galtone","email":"fgaltone1d@businessinsider.com","gender":"Non-binary","location":"Germany","username":"fgaltone1d","image":"http://dummyimage.com/194x234.png/5fa2dd/ffffff","native":false},
{"id":51,"full_name":"Crichton MacCallum","email":"cmaccallum1e@storify.com","gender":"Polygender","location":"Germany","username":"cmaccallum1e","image":"http://dummyimage.com/156x163.png/5fa2dd/ffffff","native":true},
{"id":52,"full_name":"Albina Koppke","email":"akoppke1f@icio.us","gender":"Agender","location":"Germany","username":"akoppke1f","image":"http://dummyimage.com/123x120.png/dddddd/000000","native":true},
{"id":53,"full_name":"Addy Adlem","email":"aadlem1g@lycos.com","gender":"Female","location":"Germany","username":"aadlem1g","image":"http://dummyimage.com/210x240.png/5fa2dd/ffffff","native":true},
{"id":54,"full_name":"Sigmund Bonanno","email":"sbonanno1h@usatoday.com","gender":"Non-binary","location":"Germany","username":"sbonanno1h","image":"http://dummyimage.com/248x278.png/5fa2dd/ffffff","native":true},
{"id":55,"full_name":"Ariadne Cankett","email":"acankett1i@techcrunch.com","gender":"Non-binary","location":"Germany","username":"acankett1i","image":"http://dummyimage.com/220x173.png/ff4444/ffffff","native":true},
{"id":56,"full_name":"Hort Rehm","email":"hrehm1j@nba.com","gender":"Genderfluid","location":"Germany","username":"hrehm1j","image":"http://dummyimage.com/176x300.png/ff4444/ffffff","native":false},
{"id":57,"full_name":"Kristian Kirsche","email":"kkirsche1k@house.gov","gender":"Male","location":"Germany","username":"kkirsche1k","image":"http://dummyimage.com/108x272.png/5fa2dd/ffffff","native":true},
{"id":58,"full_name":"Bethany Brane","email":"bbrane1l@ftc.gov","gender":"Polygender","location":"Germany","username":"bbrane1l","image":"http://dummyimage.com/106x104.png/ff4444/ffffff","native":false},
{"id":59,"full_name":"Cordelie Barwick","email":"cbarwick1m@msn.com","gender":"Polygender","location":"Germany","username":"cbarwick1m","image":"http://dummyimage.com/133x163.png/ff4444/ffffff","native":false},
{"id":60,"full_name":"Lynnea Jecock","email":"ljecock1n@delicious.com","gender":"Agender","location":"Germany","username":"ljecock1n","image":"http://dummyimage.com/189x122.png/cc0000/ffffff","native":true},
{"id":61,"full_name":"Trisha Ruffell","email":"truffell1o@youtu.be","gender":"Non-binary","location":"Germany","username":"truffell1o","image":"http://dummyimage.com/162x117.png/dddddd/000000","native":false},
{"id":62,"full_name":"Austine Metheringham","email":"ametheringham1p@spiegel.de","gender":"Female","location":"Germany","username":"ametheringham1p","image":"http://dummyimage.com/201x191.png/dddddd/000000","native":false},
{"id":63,"full_name":"Nolana Adolthine","email":"nadolthine1q@sakura.ne.jp","gender":"Bigender","location":"Germany","username":"nadolthine1q","image":"http://dummyimage.com/230x136.png/ff4444/ffffff","native":true},
{"id":64,"full_name":"Billie Steabler","email":"bsteabler1r@wufoo.com","gender":"Genderfluid","location":"Germany","username":"bsteabler1r","image":"http://dummyimage.com/181x241.png/ff4444/ffffff","native":true},
{"id":65,"full_name":"Riccardo Siddle","email":"rsiddle1s@prlog.org","gender":"Genderqueer","location":"Germany","username":"rsiddle1s","image":"http://dummyimage.com/163x304.png/dddddd/000000","native":false},
{"id":66,"full_name":"Letty Mattheeuw","email":"lmattheeuw1t@google.it","gender":"Genderqueer","location":"Germany","username":"lmattheeuw1t","image":"http://dummyimage.com/208x290.png/5fa2dd/ffffff","native":true},
{"id":67,"full_name":"Jock Fulep","email":"jfulep1u@hao123.com","gender":"Non-binary","location":"Germany","username":"jfulep1u","image":"http://dummyimage.com/153x211.png/5fa2dd/ffffff","native":true},
{"id":68,"full_name":"Roby Tessyman","email":"rtessyman1v@imgur.com","gender":"Polygender","location":"Germany","username":"rtessyman1v","image":"http://dummyimage.com/109x162.png/5fa2dd/ffffff","native":false},
{"id":69,"full_name":"Jefferey Knellen","email":"jknellen1w@techcrunch.com","gender":"Polygender","location":"Germany","username":"jknellen1w","image":"http://dummyimage.com/188x181.png/dddddd/000000","native":true},
{"id":70,"full_name":"Roxanne Puckinghorne","email":"rpuckinghorne1x@eventbrite.com","gender":"Genderfluid","location":"Germany","username":"rpuckinghorne1x","image":"http://dummyimage.com/160x189.png/dddddd/000000","native":true},
{"id":71,"full_name":"Alleyn Melley","email":"amelley1y@vistaprint.com","gender":"Polygender","location":"Germany","username":"amelley1y","image":"http://dummyimage.com/100x319.png/cc0000/ffffff","native":false},
{"id":72,"full_name":"Chrysler Murdie","email":"cmurdie1z@salon.com","gender":"Genderqueer","location":"Germany","username":"cmurdie1z","image":"http://dummyimage.com/138x326.png/ff4444/ffffff","native":true},
{"id":73,"full_name":"Nicko Dovington","email":"ndovington20@last.fm","gender":"Bigender","location":"Germany","username":"ndovington20","image":"http://dummyimage.com/149x215.png/dddddd/000000","native":false},
{"id":74,"full_name":"Geri Burrus","email":"gburrus21@cnet.com","gender":"Genderqueer","location":"Germany","username":"gburrus21","image":"http://dummyimage.com/156x107.png/5fa2dd/ffffff","native":false},
{"id":75,"full_name":"Heather Cropton","email":"hcropton22@t.co","gender":"Polygender","location":"Germany","username":"hcropton22","image":"http://dummyimage.com/208x112.png/dddddd/000000","native":false},
{"id":76,"full_name":"Tildi Winterburn","email":"twinterburn23@ucoz.ru","gender":"Genderqueer","location":"Germany","username":"twinterburn23","image":"http://dummyimage.com/139x132.png/dddddd/000000","native":false},
{"id":77,"full_name":"Jennee Pimm","email":"jpimm24@hhs.gov","gender":"Bigender","location":"Germany","username":"jpimm24","image":"http://dummyimage.com/170x159.png/ff4444/ffffff","native":true},
{"id":78,"full_name":"Winfred Ladyman","email":"wladyman25@dot.gov","gender":"Agender","location":"Germany","username":"wladyman25","image":"http://dummyimage.com/160x348.png/ff4444/ffffff","native":false},
{"id":79,"full_name":"Mora West","email":"mwest26@cbsnews.com","gender":"Female","location":"Germany","username":"mwest26","image":"http://dummyimage.com/102x325.png/5fa2dd/ffffff","native":true},
{"id":80,"full_name":"Natale Craighead","email":"ncraighead27@latimes.com","gender":"Female","location":"Germany","username":"ncraighead27","image":"http://dummyimage.com/101x310.png/ff4444/ffffff","native":true},
{"id":81,"full_name":"Lucho Dean","email":"ldean28@epa.gov","gender":"Genderfluid","location":"Germany","username":"ldean28","image":"http://dummyimage.com/226x117.png/dddddd/000000","native":false},
{"id":82,"full_name":"Rice Tremble","email":"rtremble29@usgs.gov","gender":"Agender","location":"Germany","username":"rtremble29","image":"http://dummyimage.com/179x283.png/dddddd/000000","native":false},
{"id":83,"full_name":"Alika Rawdales","email":"arawdales2a@dedecms.com","gender":"Genderqueer","location":"Germany","username":"arawdales2a","image":"http://dummyimage.com/199x293.png/5fa2dd/ffffff","native":false},
{"id":84,"full_name":"Melessa MacCurtain","email":"mmaccurtain2b@eventbrite.com","gender":"Non-binary","location":"Germany","username":"mmaccurtain2b","image":"http://dummyimage.com/145x206.png/5fa2dd/ffffff","native":true},
{"id":85,"full_name":"Valentin Elleyne","email":"velleyne2c@va.gov","gender":"Female","location":"Germany","username":"velleyne2c","image":"http://dummyimage.com/171x302.png/ff4444/ffffff","native":true},
{"id":86,"full_name":"Jordan Tunuy","email":"jtunuy2d@google.co.jp","gender":"Female","location":"Germany","username":"jtunuy2d","image":"http://dummyimage.com/135x261.png/dddddd/000000","native":true},
{"id":87,"full_name":"Yoshi Blanning","email":"yblanning2e@upenn.edu","gender":"Genderfluid","location":"Germany","username":"yblanning2e","image":"http://dummyimage.com/109x112.png/5fa2dd/ffffff","native":true},
{"id":88,"full_name":"Lonee Andrzejak","email":"landrzejak2f@jimdo.com","gender":"Non-binary","location":"Germany","username":"landrzejak2f","image":"http://dummyimage.com/247x140.png/ff4444/ffffff","native":false},
{"id":89,"full_name":"Stephannie Paynter","email":"spaynter2g@hud.gov","gender":"Female","location":"Germany","username":"spaynter2g","image":"http://dummyimage.com/237x289.png/5fa2dd/ffffff","native":false},
{"id":90,"full_name":"Waylon Foulds","email":"wfoulds2h@fda.gov","gender":"Polygender","location":"Germany","username":"wfoulds2h","image":"http://dummyimage.com/197x341.png/5fa2dd/ffffff","native":false},
{"id":91,"full_name":"Cissiee Sterland","email":"csterland2i@imageshack.us","gender":"Male","location":"Germany","username":"csterland2i","image":"http://dummyimage.com/142x165.png/cc0000/ffffff","native":true},
{"id":92,"full_name":"Alfonso Mantram","email":"amantram2j@a8.net","gender":"Non-binary","location":"Germany","username":"amantram2j","image":"http://dummyimage.com/135x146.png/ff4444/ffffff","native":false},
{"id":93,"full_name":"Chaddy Hoyland","email":"choyland2k@tinyurl.com","gender":"Genderqueer","location":"Germany","username":"choyland2k","image":"http://dummyimage.com/111x156.png/ff4444/ffffff","native":false},
{"id":94,"full_name":"Dione Skelcher","email":"dskelcher2l@telegraph.co.uk","gender":"Non-binary","location":"Germany","username":"dskelcher2l","image":"http://dummyimage.com/118x150.png/5fa2dd/ffffff","native":true},
{"id":95,"full_name":"Antonietta Krystof","email":"akrystof2m@rambler.ru","gender":"Male","location":"Germany","username":"akrystof2m","image":"http://dummyimage.com/169x290.png/dddddd/000000","native":true},
{"id":96,"full_name":"Gibb Lippo","email":"glippo2n@discovery.com","gender":"Agender","location":"Germany","username":"glippo2n","image":"http://dummyimage.com/155x206.png/dddddd/000000","native":true},
{"id":97,"full_name":"Dicky Judgkins","email":"djudgkins2o@livejournal.com","gender":"Genderqueer","location":"Germany","username":"djudgkins2o","image":"http://dummyimage.com/125x330.png/ff4444/ffffff","native":false},
{"id":98,"full_name":"Baudoin Sconce","email":"bsconce2p@google.com.au","gender":"Female","location":"Germany","username":"bsconce2p","image":"http://dummyimage.com/136x150.png/cc0000/ffffff","native":true},
{"id":99,"full_name":"Cammy Billam","email":"cbillam2q@techcrunch.com","gender":"Agender","location":"Germany","username":"cbillam2q","image":"http://dummyimage.com/132x317.png/dddddd/000000","native":false},
{"id":100,"full_name":"Ignacio Firpo","email":"ifirpo2r@barnesandnoble.com","gender":"Agender","location":"Germany","username":"ifirpo2r","image":"http://dummyimage.com/122x341.png/cc0000/ffffff","native":false}]